boxwine/__init__.py
boxwine-0.0.1.dist-info/LICENSE
boxwine-0.0.1.dist-info/METADATA
boxwine-0.0.1.dist-info/WHEEL
boxwine-0.0.1.dist-info/top_level.txt
boxwine-0.0.1.dist-info/RECORD
