Metadata-Version: 2.1
Name: boxwine
Version: 0.0.1
Summary: Turn your Wine apps into Mac apps
Home-page: https://github.com/rishabh/boxwine
Author: Rishabh Moudgil
Author-email: me@rishabhmoudgil.com
License: UNKNOWN
Platform: UNKNOWN
Classifier: Programming Language :: Python :: 2
Classifier: Programming Language :: Python :: 3
Classifier: License :: OSI Approved :: GNU General Public License v3 (GPLv3)
Classifier: Operating System :: OS Independent
Requires-Python: >=2
